printUNIinCS/__init__.py
printUNIinCS/print_message.py
printUNIinCS-0.0.1.dist-info/METADATA
printUNIinCS-0.0.1.dist-info/WHEEL
printUNIinCS-0.0.1.dist-info/top_level.txt
printUNIinCS-0.0.1.dist-info/RECORD
